[
    {
        "timestamp": "2024-12-31T00:51:17.127573",
        "area_bangla": "ঢাকা মেট্রো-গ",
        "area_english": "Dhaka Metro-G",
        "number_bangla": "২০-০১১৬",
        "number_english": "20-0116",
        "original_text": "ঢাকা মেট্রো-গ ২০-০১১৬"
    },
    {
        "timestamp": "2024-12-31T00:51:26.019732",
        "area_bangla": "ঢাকা মেট্রো-গ",
        "area_english": "Dhaka Metro-G",
        "number_bangla": "২০-০১১৬",
        "number_english": "20-0116",
        "original_text": "ঢাকা মেট্রো-গ ২০-০১১৬"
    },
    {
        "timestamp": "2024-12-31T00:54:58.327961",
        "area_bangla": "ঢাকা মেট্রো-গ",
        "area_english": "Dhaka Metro-G",
        "number_bangla": "২০-০১১৬",
        "number_english": "20-0116",
        "original_text": "ঢাকা মেট্রো-গ ২০-০১১৬"
    },
    {
        "timestamp": "2025-01-05T14:28:10.125176",
        "area_bangla": "ঢাকা মেট্রো-হ",
        "area_english": "Dhaka Metro-H",
        "number_bangla": "৩৭-৫৯৭৪",
        "number_english": "37-5974",
        "original_text": "ঢাকা মেড্রেো ৩৭-৫৯৭৪"
    },
    {
        "timestamp": "2025-01-05T14:28:26.499666",
        "area_bangla": "ঢাকা মেট্রো-হ",
        "area_english": "Dhaka Metro-H",
        "number_bangla": "৩৭-৫৯৭৪",
        "number_english": "37-5974",
        "original_text": "ঢাকা মেডরেী: ৩৭-৫৯৭৪"
    },
    {
        "timestamp": "2025-01-05T14:28:38.245831",
        "area_bangla": "ঢাকা মেট্রো-হ",
        "area_english": "Dhaka Metro-H",
        "number_bangla": "৩৭-৫৯৭৪",
        "number_english": "37-5974",
        "original_text": "ঢাকা মেন্ট্রী ৩৭-৫৯৭৪"
    },
    {
        "timestamp": "2025-01-05T14:28:43.907364",
        "area_bangla": "ঢাকা মেট্রো-ন",
        "area_english": "Dhaka Metro-N",
        "number_bangla": "৩৭-৫৯৭৪",
        "number_english": "37-5974",
        "original_text": "ঢাকা মেন ৩৭-৫৯৭৪"
    },
    {
        "timestamp": "2025-01-05T14:28:49.601305",
        "area_bangla": "ঢাকা মেট্রো-হ",
        "area_english": "Dhaka Metro-H",
        "number_bangla": "৩৭-৫৯৭৪",
        "number_english": "37-5974",
        "original_text": "ঢাকা মে্ডেো ৩৭-৫৯৭৪"
    },
    {
        "timestamp": "2025-01-05T14:28:55.245428",
        "area_bangla": "ঢাকা মেট্রো-হ",
        "area_english": "Dhaka Metro-H",
        "number_bangla": "৩৭-৫৯৭৪",
        "number_english": "37-5974",
        "original_text": "ঢাকা মেন্ডেো ৩৭-৫৯৭৪"
    },
    {
        "timestamp": "2025-01-05T14:29:01.034341",
        "area_bangla": "ঢাকা মেট্রো-ড",
        "area_english": "Dhaka Metro-D",
        "number_bangla": "৩৭-৫৯৭৪",
        "number_english": "37-5974",
        "original_text": "ঢাক] মেন্ডে] ৩৭-৫৯৭৪"
    },
    {
        "timestamp": "2025-01-05T14:29:26.753611",
        "area_bangla": "ঢাকা মেট্রো-হ",
        "area_english": "Dhaka Metro-H",
        "number_bangla": "৩৭-৫৯৭৪",
        "number_english": "37-5974",
        "original_text": "ঢাঙ] মেনড্রা ৩৭-৫৯৭৪"
    },
    {
        "timestamp": "2025-01-05T14:29:32.900726",
        "area_bangla": "ঢাকা মেট্রো-হ",
        "area_english": "Dhaka Metro-H",
        "number_bangla": "৩৭-৫৯৭৪",
        "number_english": "37-5974",
        "original_text": "ঢাঙা সেট্রো ৩৭-৫৯৭৪"
    },
    {
        "timestamp": "2025-01-05T14:29:39.018169",
        "area_bangla": "ঢাকা মেট্রো-হ",
        "area_english": "Dhaka Metro-H",
        "number_bangla": "৩৭-৫৯৭৪",
        "number_english": "37-5974",
        "original_text": "ঢাঙ মেট্রো ৩৭-৫৯৭৪"
    },
    {
        "timestamp": "2025-01-05T14:29:45.269956",
        "area_bangla": "ঢাকা মেট্রো-হ",
        "area_english": "Dhaka Metro-H",
        "number_bangla": "৩৭-৫৯৭৪",
        "number_english": "37-5974",
        "original_text": "ঢাঙ মেন্ট্রী ৩৭-৫৯৭৪"
    },
    {
        "timestamp": "2025-01-05T14:29:53.801798",
        "area_bangla": "ঢাকা মেট্রো-হ",
        "area_english": "Dhaka Metro-H",
        "number_bangla": "৩৭-৫৯৭৪",
        "number_english": "37-5974",
        "original_text": "ঢাঙ মেন্ট্র: ৩৭-৫৯৭৪"
    },
    {
        "timestamp": "2025-01-05T14:30:02.766139",
        "area_bangla": "ঢাকা মেট্রো-হ",
        "area_english": "Dhaka Metro-H",
        "number_bangla": "৩৭-৫৯৭৪",
        "number_english": "37-5974",
        "original_text": "ঢাঙ মে্ট্রা: ৩৭-৫৯৭৪"
    },
    {
        "timestamp": "2025-01-05T14:30:38.798131",
        "area_bangla": "ঢাকা মেট্রো-হ",
        "area_english": "Dhaka Metro-H",
        "number_bangla": "৩৭-৫৯৭৪",
        "number_english": "37-5974",
        "original_text": "ঢাশা মেনটরী ৩৭-৫৯৭৪"
    },
    {
        "timestamp": "2025-01-05T14:35:39.785190",
        "area_bangla": "ঢাকা মেট্রো-হ",
        "area_english": "Dhaka Metro-H",
        "number_bangla": "৩৭-৫৯৭৪",
        "number_english": "37-5974",
        "original_text": "ঢাকা মেডরেী: ৩৭-৫৯৭৪"
    },
    {
        "timestamp": "2025-01-05T14:35:45.990211",
        "area_bangla": "ঢাকা মেট্রো-হ",
        "area_english": "Dhaka Metro-H",
        "number_bangla": "৩৭-৫৯৭৪",
        "number_english": "37-5974",
        "original_text": "ঢাকা মেন্ট্রী ৩৭-৫৯৭৪"
    },
    {
        "timestamp": "2025-01-05T14:35:52.315895",
        "area_bangla": "ঢাকা মেট্রো-হ",
        "area_english": "Dhaka Metro-H",
        "number_bangla": "৩৭-৫৯৭৪",
        "number_english": "37-5974",
        "original_text": "ঢাকা মে্ডেো ৩৭-৫৯৭৪"
    },
    {
        "timestamp": "2025-01-05T15:02:10.477422",
        "area_bangla": "ঢাকা মেট্রো-গ",
        "area_english": "Dhaka Metro-G",
        "number_bangla": "২০-০১১৬",
        "number_english": "20-0116",
        "original_text": "ঢাকা মেট্রো-গ ২০-০১১৬"
    },
    {
        "timestamp": "2025-01-05T15:02:18.537779",
        "area_bangla": "ঢাকা মেট্রো-গ",
        "area_english": "Dhaka Metro-G",
        "number_bangla": "২০-০১১৬",
        "number_english": "20-0116",
        "original_text": "ঢাকা মেট্রো-গ ২০-০১১৬"
    },
    {
        "timestamp": "2025-01-05T15:14:58.832315",
        "area_bangla": "চুয়াডাংগা-ল",
        "area_english": "Chuadangga-L",
        "number_bangla": "১২১১৭৭৪",
        "number_english": "1211774",
        "original_text": "চুয়াডাংগা: ল ১২১১৭৭৪"
    },
    {
        "timestamp": "2025-01-06T22:48:42.875043",
        "area_bangla": "ঢাকা মেট্রো-হ",
        "area_english": "Dhaka Metro-H",
        "number_bangla": "২২-৬৪৫৭",
        "number_english": "22-6457",
        "original_text": "ঢাকা শেদ্রেো ২২-৬৪৫৭"
    },
    {
        "timestamp": "2025-01-06T22:48:49.570220",
        "area_bangla": "ঢাকা মেট্রো-হ",
        "area_english": "Dhaka Metro-H",
        "number_bangla": "২২-৬৪৫৭",
        "number_english": "22-6457",
        "original_text": "ঢাকা শেদরেো ২২-৬৪৫৭"
    },
    {
        "timestamp": "2025-01-06T22:48:56.116487",
        "area_bangla": "ঢাকা মেট্রো-হ",
        "area_english": "Dhaka Metro-H",
        "number_bangla": "২২-৬৪৫৭",
        "number_english": "22-6457",
        "original_text": "ঢাকা মেদরেী ২২-৬৪৫৭"
    },
    {
        "timestamp": "2025-01-06T22:49:10.056248",
        "area_bangla": "ঢাকা মেট্রো-হ",
        "area_english": "Dhaka Metro-H",
        "number_bangla": "২২-৬৪৫৭",
        "number_english": "22-6457",
        "original_text": "ঢাকা শেদ্রেো ২২-৬৪৫৭"
    },
    {
        "timestamp": "2025-01-06T22:49:16.864118",
        "area_bangla": "ঢাকা মেট্রো-দ",
        "area_english": "Dhaka Metro-D",
        "number_bangla": "২২-৬৪৫৭",
        "number_english": "22-6457",
        "original_text": "ঢানা মেদ] ২২-৬৪৫৭"
    },
    {
        "timestamp": "2025-01-06T22:54:39.646137",
        "area_bangla": "ঢাকা মেট্রো-হ",
        "area_english": "Dhaka Metro-H",
        "number_bangla": "৩২-৭৫১৩",
        "number_english": "32-7513",
        "original_text": "ঢাকা মেট্রেো: ৩২-৭৫১৩"
    },
    {
        "timestamp": "2025-01-06T22:54:47.076493",
        "area_bangla": "ঢাকা মেট্রো-হ",
        "area_english": "Dhaka Metro-H",
        "number_bangla": "৩২-৭৫১৩",
        "number_english": "32-7513",
        "original_text": "ঢাকা মেট্রেো: ৩২-৭৫১৩"
    },
    {
        "timestamp": "2025-01-06T22:54:56.768220",
        "area_bangla": "ঢাকা মেট্রো-হ",
        "area_english": "Dhaka Metro-H",
        "number_bangla": "৩২-৭৫১৩",
        "number_english": "32-7513",
        "original_text": "ঢাকা মেট্রেো: ৩২-৭৫১৩"
    },
    {
        "timestamp": "2025-01-06T22:55:06.509055",
        "area_bangla": "ঢাকা মেট্রো-হ",
        "area_english": "Dhaka Metro-H",
        "number_bangla": "৩২-৭৫১৩",
        "number_english": "32-7513",
        "original_text": "ঢাকা মেট্রেো: ৩২-৭৫১৩"
    },
    {
        "timestamp": "2025-01-06T22:55:15.950672",
        "area_bangla": "ঢাকা মেট্রো-হ",
        "area_english": "Dhaka Metro-H",
        "number_bangla": "৩২-৭৫১৩",
        "number_english": "32-7513",
        "original_text": "ঢাকা মেট্রেো: ৩২-৭৫১৩"
    },
    {
        "timestamp": "2025-01-06T22:55:25.130596",
        "area_bangla": "ঢাকা মেট্রো-হ",
        "area_english": "Dhaka Metro-H",
        "number_bangla": "৩২-৭৫১৩",
        "number_english": "32-7513",
        "original_text": "ঢাকা মেট্রেো: ৩২-৭৫১৩"
    },
    {
        "timestamp": "2025-01-06T22:55:33.730088",
        "area_bangla": "ঢাকা মেট্রো-হ",
        "area_english": "Dhaka Metro-H",
        "number_bangla": "৩২-৭৫১৩",
        "number_english": "32-7513",
        "original_text": "ঢাকা মেট্রেো: ৩২-৭৫১৩"
    },
    {
        "timestamp": "2025-01-06T22:55:41.682515",
        "area_bangla": "ঢাকা মেট্রো-হ",
        "area_english": "Dhaka Metro-H",
        "number_bangla": "৩২-৭৫১৩",
        "number_english": "32-7513",
        "original_text": "ঢাকা মেট্রেো: ৩২-৭৫১৩"
    },
    {
        "timestamp": "2025-01-07T00:17:47.484551",
        "area_bangla": "ঢাকা মেট্রো-হ",
        "area_english": "Dhaka Metro-H",
        "number_bangla": "৩২-৭৫১৩",
        "number_english": "32-7513",
        "original_text": "ঢাকা মেট্রেো: ৩২-৭৫১৩"
    },
    {
        "timestamp": "2025-01-07T00:17:55.108054",
        "area_bangla": "ঢাকা মেট্রো-হ",
        "area_english": "Dhaka Metro-H",
        "number_bangla": "৩২-৭৫১৩",
        "number_english": "32-7513",
        "original_text": "ঢাকা মেট্রেো: ৩২-৭৫১৩"
    },
    {
        "timestamp": "2025-01-07T00:18:03.161430",
        "area_bangla": "ঢাকা মেট্রো-হ",
        "area_english": "Dhaka Metro-H",
        "number_bangla": "৩২-৭৫১৩",
        "number_english": "32-7513",
        "original_text": "ঢাকা মেট্রেো: ৩২-৭৫১৩"
    },
    {
        "timestamp": "2025-01-07T00:18:12.897840",
        "area_bangla": "ঢাকা মেট্রো-হ",
        "area_english": "Dhaka Metro-H",
        "number_bangla": "৩২-৭৫১৩",
        "number_english": "32-7513",
        "original_text": "ঢাকা মেট্রেো: ৩২-৭৫১৩"
    },
    {
        "timestamp": "2025-01-07T00:18:20.713471",
        "area_bangla": "ঢাকা মেট্রো-হ",
        "area_english": "Dhaka Metro-H",
        "number_bangla": "৩২-৭৫১৩",
        "number_english": "32-7513",
        "original_text": "ঢাকা মেট্রেো: ৩২-৭৫১৩"
    },
    {
        "timestamp": "2025-01-07T00:26:38.752486",
        "area_bangla": "ঢাকা মেট্রো-হ",
        "area_english": "Dhaka Metro-H",
        "number_bangla": "৩২-৭৫১৩",
        "number_english": "32-7513",
        "original_text": "ঢাকা মেট্রেো: ৩২-৭৫১৩",
        "speed": 0
    },
    {
        "timestamp": "2025-01-07T00:27:26.465136",
        "area_bangla": "চট্র মেট্রো-গ",
        "area_english": "Chittor Metro-G",
        "number_bangla": "১১-৭২৮৮",
        "number_english": "11-7288",
        "original_text": "চট্ট মেট্রো গ ১১-৭২৮৮",
        "speed": 0
    },
    {
        "timestamp": "2025-01-07T00:27:32.560909",
        "area_bangla": "চট্র মেট্রো-গ",
        "area_english": "Chittor Metro-G",
        "number_bangla": "১১-৭২৮৮",
        "number_english": "11-7288",
        "original_text": "চট্ট মেট্রো গ ১১-৭২৮৮",
        "speed": 0
    },
    {
        "timestamp": "2025-01-07T00:27:40.755407",
        "area_bangla": "চট্র মেট্রো-গ",
        "area_english": "Chittor Metro-G",
        "number_bangla": "১১-৭২৮৮",
        "number_english": "11-7288",
        "original_text": "চট্ট মেট্রো গ ১১-৭২৮৮",
        "speed": 0
    },
    {
        "timestamp": "2025-01-07T00:50:30.418268",
        "area_bangla": "ঢাকা মেট্রো-হ",
        "area_english": "Dhaka Metro-H",
        "number_bangla": "২২-৬৪৫৭",
        "number_english": "22-6457",
        "original_text": "ঢাকা শেদ্রেো ২২-৬৪৫৭",
        "speed": 21.6
    },
    {
        "timestamp": "2025-01-07T00:50:41.169947",
        "area_bangla": "ঢাকা মেট্রো-হ",
        "area_english": "Dhaka Metro-H",
        "number_bangla": "২২-৬৪৫৭",
        "number_english": "22-6457",
        "original_text": "ঢাকা শেদরেো ২২-৬৪৫৭",
        "speed": 0.0
    },
    {
        "timestamp": "2025-01-07T00:50:47.665756",
        "area_bangla": "ঢাকা মেট্রো-হ",
        "area_english": "Dhaka Metro-H",
        "number_bangla": "২২-৬৪৫৭",
        "number_english": "22-6457",
        "original_text": "ঢাকা মেদরেী ২২-৬৪৫৭",
        "speed": 0.0
    },
    {
        "timestamp": "2025-01-07T01:05:42.749421",
        "area_bangla": "ঢাকা মেট্রো-হ",
        "area_english": "Dhaka Metro-H",
        "number_bangla": "২২-৬৪৫৭",
        "number_english": "22-6457",
        "original_text": "ঢাকা শেদ্রেো ২২-৬৪৫৭",
        "speed": 21.6
    },
    {
        "timestamp": "2025-01-07T01:05:48.683579",
        "area_bangla": "ঢাকা মেট্রো-হ",
        "area_english": "Dhaka Metro-H",
        "number_bangla": "২২-৬৪৫৭",
        "number_english": "22-6457",
        "original_text": "ঢাকা শেদরেো ২২-৬৪৫৭",
        "speed": 0.0
    },
    {
        "timestamp": "2025-01-07T01:05:54.468763",
        "area_bangla": "ঢাকা মেট্রো-হ",
        "area_english": "Dhaka Metro-H",
        "number_bangla": "২২-৬৪৫৭",
        "number_english": "22-6457",
        "original_text": "ঢাকা মেদরেী ২২-৬৪৫৭",
        "speed": 0.0
    },
    {
        "timestamp": "2025-01-07T01:06:07.327397",
        "area_bangla": "ঢাকা মেট্রো-হ",
        "area_english": "Dhaka Metro-H",
        "number_bangla": "২২-৬৪৫৭",
        "number_english": "22-6457",
        "original_text": "ঢাকা শেদ্রেো ২২-৬৪৫৭",
        "speed": 0.0
    },
    {
        "timestamp": "2025-01-07T01:06:13.392882",
        "area_bangla": "ঢাকা মেট্রো-দ",
        "area_english": "Dhaka Metro-D",
        "number_bangla": "২২-৬৪৫৭",
        "number_english": "22-6457",
        "original_text": "ঢানা মেদ] ২২-৬৪৫৭",
        "speed": 15.27
    },
    {
        "timestamp": "2025-01-07T01:24:35.954860",
        "area_bangla": "ঢাকা মেট্রো-হ",
        "area_english": "Dhaka Metro-H",
        "number_bangla": "২২-৬৪৫৭",
        "number_english": "22-6457",
        "original_text": "ঢাকা শেদ্রেো ২২-৬৪৫৭",
        "speed": 21.6
    },
    {
        "timestamp": "2025-01-07T01:24:44.370316",
        "area_bangla": "ঢাকা মেট্রো-হ",
        "area_english": "Dhaka Metro-H",
        "number_bangla": "২২-৬৪৫৭",
        "number_english": "22-6457",
        "original_text": "ঢাকা শেদরেো ২২-৬৪৫৭",
        "speed": 0.0
    },
    {
        "timestamp": "2025-01-07T01:27:55.583842",
        "area_bangla": "ঢাকা মেট্রো-হ",
        "area_english": "Dhaka Metro-H",
        "number_bangla": "২২-৬৪৫৭",
        "number_english": "22-6457",
        "original_text": "ঢাকা শেদ্রেো ২২-৬৪৫৭",
        "speed": 21.6
    },
    {
        "timestamp": "2025-01-07T01:28:02.450914",
        "area_bangla": "ঢাকা মেট্রো-হ",
        "area_english": "Dhaka Metro-H",
        "number_bangla": "২২-৬৪৫৭",
        "number_english": "22-6457",
        "original_text": "ঢাকা শেদরেো ২২-৬৪৫৭",
        "speed": 0.0
    },
    {
        "timestamp": "2025-01-07T01:28:08.189618",
        "area_bangla": "ঢাকা মেট্রো-হ",
        "area_english": "Dhaka Metro-H",
        "number_bangla": "২২-৬৪৫৭",
        "number_english": "22-6457",
        "original_text": "ঢাকা মেদরেী ২২-৬৪৫৭",
        "speed": 0.0
    },
    {
        "timestamp": "2025-01-07T01:29:36.281590",
        "area_bangla": "ঢাকা মেট্রো-হ",
        "area_english": "Dhaka Metro-H",
        "number_bangla": "২২-৬৪৫৭",
        "number_english": "22-6457",
        "original_text": "ঢাকা শেদ্রেো ২২-৬৪৫৭",
        "speed": 21.6
    },
    {
        "timestamp": "2025-01-07T01:29:42.008817",
        "area_bangla": "ঢাকা মেট্রো-হ",
        "area_english": "Dhaka Metro-H",
        "number_bangla": "২২-৬৪৫৭",
        "number_english": "22-6457",
        "original_text": "ঢাকা শেদরেো ২২-৬৪৫৭",
        "speed": 0.0
    },
    {
        "timestamp": "2025-01-07T01:29:47.717300",
        "area_bangla": "ঢাকা মেট্রো-হ",
        "area_english": "Dhaka Metro-H",
        "number_bangla": "২২-৬৪৫৭",
        "number_english": "22-6457",
        "original_text": "ঢাকা মেদরেী ২২-৬৪৫৭",
        "speed": 0.0
    },
    {
        "timestamp": "2025-01-07T01:30:01.668358",
        "area_bangla": "ঢাকা মেট্রো-হ",
        "area_english": "Dhaka Metro-H",
        "number_bangla": "২২-৬৪৫৭",
        "number_english": "22-6457",
        "original_text": "ঢাকা শেদ্রেো ২২-৬৪৫৭",
        "speed": 0.0
    },
    {
        "timestamp": "2025-01-07T01:32:38.535617",
        "area_bangla": "ঢাকা মেট্রো-হ",
        "area_english": "Dhaka Metro-H",
        "number_bangla": "২২-৬৪৫৭",
        "number_english": "22-6457",
        "original_text": "ঢাকা শেদ্রেো ২২-৬৪৫৭",
        "speed": 21.6
    },
    {
        "timestamp": "2025-01-07T01:32:45.099380",
        "area_bangla": "ঢাকা মেট্রো-হ",
        "area_english": "Dhaka Metro-H",
        "number_bangla": "২২-৬৪৫৭",
        "number_english": "22-6457",
        "original_text": "ঢাকা শেদরেো ২২-৬৪৫৭",
        "speed": 0.0
    },
    {
        "timestamp": "2025-01-07T01:32:51.659001",
        "area_bangla": "ঢাকা মেট্রো-হ",
        "area_english": "Dhaka Metro-H",
        "number_bangla": "২২-৬৪৫৭",
        "number_english": "22-6457",
        "original_text": "ঢাকা মেদরেী ২২-৬৪৫৭",
        "speed": 0.0
    },
    {
        "timestamp": "2025-01-07T01:33:04.830411",
        "area_bangla": "ঢাকা মেট্রো-হ",
        "area_english": "Dhaka Metro-H",
        "number_bangla": "২২-৬৪৫৭",
        "number_english": "22-6457",
        "original_text": "ঢাকা শেদ্রেো ২২-৬৪৫৭",
        "speed": 0.0
    },
    {
        "timestamp": "2025-01-07T01:33:11.218508",
        "area_bangla": "ঢাকা মেট্রো-দ",
        "area_english": "Dhaka Metro-D",
        "number_bangla": "২২-৬৪৫৭",
        "number_english": "22-6457",
        "original_text": "ঢানা মেদ] ২২-৬৪৫৭",
        "speed": 15.27
    },
    {
        "timestamp": "2025-01-07T01:35:40.658208",
        "area_bangla": "ঢাকা মেট্রো-হ",
        "area_english": "Dhaka Metro-H",
        "number_bangla": "২২-৬৪৫৭",
        "number_english": "22-6457",
        "original_text": "ঢাকা শেদ্রেো ২২-৬৪৫৭",
        "speed": 21.6
    },
    {
        "timestamp": "2025-01-07T01:35:46.913090",
        "area_bangla": "ঢাকা মেট্রো-হ",
        "area_english": "Dhaka Metro-H",
        "number_bangla": "২২-৬৪৫৭",
        "number_english": "22-6457",
        "original_text": "ঢাকা শেদরেো ২২-৬৪৫৭",
        "speed": 0.0
    }
]